tortoise_api/__init__.py
tortoise_api/api.py
tortoise_api/loader.py
tortoise_api/oauth.py
tortoise_api-0.10.17.dist-info/licenses/LICENSE
tortoise_api-0.10.17.dist-info/METADATA
tortoise_api-0.10.17.dist-info/WHEEL
tortoise_api-0.10.17.dist-info/top_level.txt
tortoise_api-0.10.17.dist-info/RECORD
