Metadata-Version: 2.4
Name: tortoise-api
Version: 0.10.17
Summary: Simplest fastest minimal REST API CRUD generator for Tortoise ORM models
Author-email: Artemiev <mixartemev@gmail.com>
License: MIT
Project-URL: Homepage, https://github.com/mixartemev/x-api
Project-URL: Repository, https://github.com/mixartemev/x-api
Keywords: starlette,fastapi,admin,generator,db-model,crud,tortoise-orm,ASGI-admin
Requires-Python: >=3.11
License-File: LICENSE
Requires-Dist: aiogram
Requires-Dist: asyncpg
Requires-Dist: fastapi
Requires-Dist: orjson
Requires-Dist: uvicorn
Requires-Dist: python-jose[cryptography]
Requires-Dist: passlib[bcrypt]
Requires-Dist: python-multipart
Requires-Dist: uvicorn
Requires-Dist: tortoise-api-model==0.9.5
Requires-Dist: xtg-auth==0.0.2
Provides-Extra: dev
Requires-Dist: build; extra == "dev"
Requires-Dist: python-dotenv; extra == "dev"
Requires-Dist: twine; extra == "dev"
Requires-Dist: setuptools_scm; extra == "dev"
Dynamic: license-file
